 {
  "allmovie" : [

{
"count" : "01",
"vol" : "Episode (01) | THe Ruins",
"video" : "http://www.mediafire.com/file/d05qtnnpuyx3q3f/The_Stranded_ep1.mp4/file"
}
,
{
"count" : "02",
"vol" : "Episode (02) | The Return",
"video" : "http://www.mediafire.com/file/2j9zwkdj017102x/The_Stranded_ep2.mp4/file"
}
,
{
"count" : "03",
"vol" : "Episode (03) | The Code",
"video" : "http://www.mediafire.com/file/tk8r7lq8pa0luev/The_Stranded_ep3.mp4/file"
}
,
{
"count" : "04",
"vol" : "Episode (04) | The Fall",
"video" : "https://www.mediafire.com/file/hucb09hpyqlaart/The_Stranded_ep4.mp4/file"
}
,
{
"count" : "05",
"vol" : "Episode (05) | THe Mutiny",
"video" : "http://www.mediafire.com/file/smz3l6r4c307346/The_Stranded_ep5.mp4/file"
}
,
{
"count" : "06",
"vol" : "Episode (06) | The Attack",
"video" : "http://www.mediafire.com/file/sg5f9yy4h6t7gqj/The_Stranded_ep6.mp4/file"
}
,
{
"count" : "07",
"vol" : "Episode (07) THe Gate",
"video" : "http://www.mediafire.com/file/f95bkcr9bkpyfcc/The_Stranded_ep7.mp4/file"
}

]
}
